onto_standard/__init__.py
onto_standard/client.py
onto_standard-10.0.0.dist-info/licenses/LICENSE
tests/__init__.py
tests/test_onto_standard.py
onto_standard-10.0.0.dist-info/METADATA
onto_standard-10.0.0.dist-info/WHEEL
onto_standard-10.0.0.dist-info/entry_points.txt
onto_standard-10.0.0.dist-info/top_level.txt
onto_standard-10.0.0.dist-info/RECORD
