Metadata-Version: 2.4
Name: onto-standard
Version: 10.0.0
Summary: ONTO Epistemic Risk Standard v10.0 Reference Implementation
Home-page: https://onto-bench.org/standard
Author: ONTO Standards Council
Author-email: ONTO Standards Council <standards@onto-bench.org>
License: Apache-2.0
Project-URL: Documentation, https://onto-bench.org/standard
Project-URL: Source, https://github.com/onto-project/onto-standard
Project-URL: Standard, https://onto-bench.org/standard/v10.0
Keywords: ai,ml,llm,calibration,uncertainty,epistemic,compliance
Classifier: Development Status :: 5 - Production/Stable
Classifier: Intended Audience :: Developers
Classifier: Intended Audience :: Science/Research
Classifier: License :: OSI Approved :: Apache Software License
Classifier: Programming Language :: Python :: 3
Classifier: Programming Language :: Python :: 3.8
Classifier: Programming Language :: Python :: 3.9
Classifier: Programming Language :: Python :: 3.10
Classifier: Programming Language :: Python :: 3.11
Classifier: Programming Language :: Python :: 3.12
Classifier: Topic :: Scientific/Engineering :: Artificial Intelligence
Classifier: Topic :: Software Development :: Quality Assurance
Requires-Python: >=3.8
License-File: LICENSE
Dynamic: author
Dynamic: home-page
Dynamic: license-file
Dynamic: requires-python
